nps/__init__.py
nps/config.py
nps/main.py
nps_cli-0.1.1.dist-info/METADATA
nps_cli-0.1.1.dist-info/WHEEL
nps_cli-0.1.1.dist-info/entry_points.txt
nps_cli-0.1.1.dist-info/top_level.txt
nps_cli-0.1.1.dist-info/RECORD
