Metadata-Version: 2.4
Name: nps-cli
Version: 0.1.1
Summary: A simple CLI for sampling point clouds from large volumetric datasets
Author: Jakob Troidl
License-Expression: MIT
Classifier: Programming Language :: Python :: 3
Requires-Python: >=3.11
Requires-Dist: click
Requires-Dist: volara
Requires-Dist: pocaduck
Provides-Extra: dev
Requires-Dist: pytest; extra == "dev"
Requires-Dist: black; extra == "dev"
Requires-Dist: build; extra == "dev"
Requires-Dist: twine; extra == "dev"
Requires-Dist: ruff; extra == "dev"
